{
    "title": "PARANOIA - HEARTSTEEL",
    "artist": "BLOOMIFY Engine",
    "mapper": "SmartGenerator",
    "audio_path": "PARANOIA - HEARTSTEEL.mp3",
    "image_path": "art.png",
    "bpm": 172.27,
    "offset_ms": 255.42,
    "song_length_ms": 198828,
    "notes": [
        {
            "time": 5851,
            "lane": 1
        },
        {
            "time": 6571,
            "lane": 2
        },
        {
            "time": 6896,
            "lane": 3
        },
        {
            "time": 7314,
            "lane": 2
        },
        {
            "time": 7523,
            "lane": 0
        },
        {
            "time": 8173,
            "lane": 2
        },
        {
            "time": 8823,
            "lane": 0
        },
        {
            "time": 9752,
            "lane": 1
        },
        {
            "time": 10983,
            "lane": 2
        },
        {
            "time": 11284,
            "lane": 1
        },
        {
            "time": 11493,
            "lane": 2
        },
        {
            "time": 12213,
            "lane": 1
        },
        {
            "time": 13630,
            "lane": 0
        },
        {
            "time": 13815,
            "lane": 2
        },
        {
            "time": 13931,
            "lane": 3
        },
        {
            "time": 14326,
            "lane": 1
        },
        {
            "time": 14837,
            "lane": 3
        },
        {
            "time": 15023,
            "lane": 0
        },
        {
            "time": 16811,
            "lane": 1
        },
        {
            "time": 16904,
            "lane": 2
        },
        {
            "time": 17136,
            "lane": 1
        },
        {
            "time": 17647,
            "lane": 0
        },
        {
            "time": 17856,
            "lane": 2
        },
        {
            "time": 18158,
            "lane": 3
        },
        {
            "time": 18227,
            "lane": 1
        },
        {
            "time": 18390,
            "lane": 2
        },
        {
            "time": 18575,
            "lane": 3
        },
        {
            "time": 18715,
            "lane": 0
        },
        {
            "time": 18831,
            "lane": 2
        },
        {
            "time": 19086,
            "lane": 1
        },
        {
            "time": 19202,
            "lane": 3
        },
        {
            "time": 19458,
            "lane": 1
        },
        {
            "time": 19644,
            "lane": 2
        },
        {
            "time": 19783,
            "lane": 1
        },
        {
            "time": 19945,
            "lane": 0
        },
        {
            "time": 20154,
            "lane": 3
        },
        {
            "time": 20340,
            "lane": 1
        },
        {
            "time": 20503,
            "lane": 0
        },
        {
            "time": 20665,
            "lane": 1
        },
        {
            "time": 21037,
            "lane": 2
        },
        {
            "time": 21339,
            "lane": 1
        },
        {
            "time": 21524,
            "lane": 3
        },
        {
            "time": 21664,
            "lane": 0
        },
        {
            "time": 21873,
            "lane": 2
        },
        {
            "time": 22082,
            "lane": 1
        },
        {
            "time": 22291,
            "lane": 0
        },
        {
            "time": 22360,
            "lane": 2
        },
        {
            "time": 22639,
            "lane": 0
        },
        {
            "time": 22801,
            "lane": 1
        },
        {
            "time": 23336,
            "lane": 2
        },
        {
            "time": 23498,
            "lane": 0
        },
        {
            "time": 23637,
            "lane": 3
        },
        {
            "time": 23870,
            "lane": 1
        },
        {
            "time": 24404,
            "lane": 2
        },
        {
            "time": 24543,
            "lane": 3
        },
        {
            "time": 24729,
            "lane": 1
        },
        {
            "time": 24915,
            "lane": 2
        },
        {
            "time": 25100,
            "lane": 3
        },
        {
            "time": 25240,
            "lane": 0
        },
        {
            "time": 25332,
            "lane": 2
        },
        {
            "time": 25611,
            "lane": 3
        },
        {
            "time": 29141,
            "lane": 1
        },
        {
            "time": 29303,
            "lane": 2
        },
        {
            "time": 29837,
            "lane": 3
        },
        {
            "time": 30557,
            "lane": 0
        },
        {
            "time": 30720,
            "lane": 2
        },
        {
            "time": 31973,
            "lane": 1
        },
        {
            "time": 32113,
            "lane": 2
        },
        {
            "time": 33715,
            "lane": 3
        },
        {
            "time": 33831,
            "lane": 0
        },
        {
            "time": 34110,
            "lane": 3
        },
        {
            "time": 34295,
            "lane": 1
        },
        {
            "time": 34411,
            "lane": 0
        },
        {
            "time": 34551,
            "lane": 1
        },
        {
            "time": 34760,
            "lane": 2
        },
        {
            "time": 34922,
            "lane": 0
        },
        {
            "time": 35085,
            "lane": 1
        },
        {
            "time": 35317,
            "lane": 2
        },
        {
            "time": 35480,
            "lane": 3
        },
        {
            "time": 35689,
            "lane": 0
        },
        {
            "time": 35874,
            "lane": 1
        },
        {
            "time": 35990,
            "lane": 3
        },
        {
            "time": 36199,
            "lane": 0
        },
        {
            "time": 36339,
            "lane": 3
        },
        {
            "time": 36501,
            "lane": 2
        },
        {
            "time": 36757,
            "lane": 3
        },
        {
            "time": 36919,
            "lane": 2
        },
        {
            "time": 37105,
            "lane": 3
        },
        {
            "time": 38336,
            "lane": 1
        },
        {
            "time": 38405,
            "lane": 3
        },
        {
            "time": 39752,
            "lane": 2
        },
        {
            "time": 40100,
            "lane": 3
        },
        {
            "time": 40263,
            "lane": 2
        },
        {
            "time": 40425,
            "lane": 0
        },
        {
            "time": 40634,
            "lane": 2
        },
        {
            "time": 40751,
            "lane": 1
        },
        {
            "time": 40960,
            "lane": 2
        },
        {
            "time": 41331,
            "lane": 3
        },
        {
            "time": 41470,
            "lane": 1
        },
        {
            "time": 41842,
            "lane": 2
        },
        {
            "time": 42051,
            "lane": 1
        },
        {
            "time": 42144,
            "lane": 2
        },
        {
            "time": 42515,
            "lane": 1
        },
        {
            "time": 42864,
            "lane": 3
        },
        {
            "time": 43096,
            "lane": 0
        },
        {
            "time": 43258,
            "lane": 2
        },
        {
            "time": 43607,
            "lane": 1
        },
        {
            "time": 43769,
            "lane": 2
        },
        {
            "time": 43955,
            "lane": 1
        },
        {
            "time": 44141,
            "lane": 3
        },
        {
            "time": 44326,
            "lane": 0
        },
        {
            "time": 44512,
            "lane": 3
        },
        {
            "time": 44628,
            "lane": 1
        },
        {
            "time": 44814,
            "lane": 2
        },
        {
            "time": 45023,
            "lane": 0
        },
        {
            "time": 45418,
            "lane": 2
        },
        {
            "time": 45580,
            "lane": 3
        },
        {
            "time": 45743,
            "lane": 0
        },
        {
            "time": 45882,
            "lane": 2
        },
        {
            "time": 46068,
            "lane": 1
        },
        {
            "time": 46463,
            "lane": 0
        },
        {
            "time": 46834,
            "lane": 2
        },
        {
            "time": 46973,
            "lane": 3
        },
        {
            "time": 47159,
            "lane": 0
        },
        {
            "time": 47461,
            "lane": 2
        },
        {
            "time": 47786,
            "lane": 1
        },
        {
            "time": 48227,
            "lane": 3
        },
        {
            "time": 48367,
            "lane": 2
        },
        {
            "time": 48506,
            "lane": 0
        },
        {
            "time": 48738,
            "lane": 2
        },
        {
            "time": 48924,
            "lane": 3
        },
        {
            "time": 49249,
            "lane": 1
        },
        {
            "time": 49458,
            "lane": 2
        },
        {
            "time": 49597,
            "lane": 1
        },
        {
            "time": 49783,
            "lane": 2
        },
        {
            "time": 49922,
            "lane": 1
        },
        {
            "time": 50155,
            "lane": 0
        },
        {
            "time": 50340,
            "lane": 2
        },
        {
            "time": 50456,
            "lane": 3
        },
        {
            "time": 50665,
            "lane": 1
        },
        {
            "time": 50874,
            "lane": 0
        },
        {
            "time": 50967,
            "lane": 3
        },
        {
            "time": 51385,
            "lane": 1
        },
        {
            "time": 51571,
            "lane": 2
        },
        {
            "time": 51710,
            "lane": 3
        },
        {
            "time": 52082,
            "lane": 0
        },
        {
            "time": 52291,
            "lane": 3
        },
        {
            "time": 52755,
            "lane": 1
        },
        {
            "time": 53104,
            "lane": 3
        },
        {
            "time": 53475,
            "lane": 2
        },
        {
            "time": 53847,
            "lane": 3
        },
        {
            "time": 54032,
            "lane": 2
        },
        {
            "time": 54218,
            "lane": 3
        },
        {
            "time": 54381,
            "lane": 1
        },
        {
            "time": 54497,
            "lane": 2
        },
        {
            "time": 54868,
            "lane": 1
        },
        {
            "time": 55240,
            "lane": 3
        },
        {
            "time": 55426,
            "lane": 1
        },
        {
            "time": 55611,
            "lane": 0
        },
        {
            "time": 55797,
            "lane": 1
        },
        {
            "time": 55936,
            "lane": 3
        },
        {
            "time": 56238,
            "lane": 1
        },
        {
            "time": 56470,
            "lane": 3
        },
        {
            "time": 56703,
            "lane": 2
        },
        {
            "time": 56842,
            "lane": 1
        },
        {
            "time": 57051,
            "lane": 3
        },
        {
            "time": 57213,
            "lane": 0
        },
        {
            "time": 57399,
            "lane": 1
        },
        {
            "time": 57748,
            "lane": 2
        },
        {
            "time": 58119,
            "lane": 1
        },
        {
            "time": 58258,
            "lane": 3
        },
        {
            "time": 58467,
            "lane": 2
        },
        {
            "time": 58792,
            "lane": 3
        },
        {
            "time": 58909,
            "lane": 2
        },
        {
            "time": 59164,
            "lane": 0
        },
        {
            "time": 60604,
            "lane": 2
        },
        {
            "time": 61463,
            "lane": 1
        },
        {
            "time": 61625,
            "lane": 0
        },
        {
            "time": 61950,
            "lane": 3
        },
        {
            "time": 62159,
            "lane": 0
        },
        {
            "time": 62879,
            "lane": 3
        },
        {
            "time": 63018,
            "lane": 2
        },
        {
            "time": 63204,
            "lane": 3
        },
        {
            "time": 63367,
            "lane": 1
        },
        {
            "time": 63738,
            "lane": 0
        },
        {
            "time": 64296,
            "lane": 2
        },
        {
            "time": 64388,
            "lane": 3
        },
        {
            "time": 64621,
            "lane": 1
        },
        {
            "time": 65317,
            "lane": 0
        },
        {
            "time": 65457,
            "lane": 2
        },
        {
            "time": 65689,
            "lane": 1
        },
        {
            "time": 65828,
            "lane": 3
        },
        {
            "time": 66037,
            "lane": 2
        },
        {
            "time": 66176,
            "lane": 3
        },
        {
            "time": 67221,
            "lane": 0
        },
        {
            "time": 67546,
            "lane": 1
        },
        {
            "time": 68847,
            "lane": 2
        },
        {
            "time": 68986,
            "lane": 1
        },
        {
            "time": 69543,
            "lane": 0
        },
        {
            "time": 69915,
            "lane": 1
        },
        {
            "time": 70101,
            "lane": 0
        },
        {
            "time": 70286,
            "lane": 3
        },
        {
            "time": 70797,
            "lane": 0
        },
        {
            "time": 70960,
            "lane": 2
        },
        {
            "time": 71308,
            "lane": 3
        },
        {
            "time": 71494,
            "lane": 1
        },
        {
            "time": 71842,
            "lane": 2
        },
        {
            "time": 72376,
            "lane": 1
        },
        {
            "time": 73630,
            "lane": 0
        },
        {
            "time": 74327,
            "lane": 1
        },
        {
            "time": 74489,
            "lane": 3
        },
        {
            "time": 75557,
            "lane": 1
        },
        {
            "time": 75720,
            "lane": 2
        },
        {
            "time": 75929,
            "lane": 1
        },
        {
            "time": 76440,
            "lane": 2
        },
        {
            "time": 76974,
            "lane": 0
        },
        {
            "time": 77159,
            "lane": 3
        },
        {
            "time": 77322,
            "lane": 0
        },
        {
            "time": 77438,
            "lane": 3
        },
        {
            "time": 77879,
            "lane": 0
        },
        {
            "time": 78529,
            "lane": 2
        },
        {
            "time": 79272,
            "lane": 3
        },
        {
            "time": 79946,
            "lane": 2
        },
        {
            "time": 80248,
            "lane": 3
        },
        {
            "time": 81362,
            "lane": 1
        },
        {
            "time": 82593,
            "lane": 3
        },
        {
            "time": 82779,
            "lane": 1
        },
        {
            "time": 83127,
            "lane": 2
        },
        {
            "time": 83638,
            "lane": 0
        },
        {
            "time": 84009,
            "lane": 3
        },
        {
            "time": 84195,
            "lane": 0
        },
        {
            "time": 84938,
            "lane": 1
        },
        {
            "time": 90766,
            "lane": 3
        },
        {
            "time": 91091,
            "lane": 2
        },
        {
            "time": 91277,
            "lane": 3
        },
        {
            "time": 91463,
            "lane": 2
        },
        {
            "time": 91927,
            "lane": 0
        },
        {
            "time": 92508,
            "lane": 3
        },
        {
            "time": 92647,
            "lane": 0
        },
        {
            "time": 94226,
            "lane": 1
        },
        {
            "time": 95178,
            "lane": 3
        },
        {
            "time": 95317,
            "lane": 1
        },
        {
            "time": 95666,
            "lane": 3
        },
        {
            "time": 96060,
            "lane": 2
        },
        {
            "time": 96223,
            "lane": 1
        },
        {
            "time": 96734,
            "lane": 0
        },
        {
            "time": 97059,
            "lane": 2
        },
        {
            "time": 97268,
            "lane": 0
        },
        {
            "time": 97407,
            "lane": 3
        },
        {
            "time": 97964,
            "lane": 2
        },
        {
            "time": 98104,
            "lane": 3
        },
        {
            "time": 98336,
            "lane": 2
        },
        {
            "time": 98452,
            "lane": 1
        },
        {
            "time": 98684,
            "lane": 2
        },
        {
            "time": 99567,
            "lane": 0
        },
        {
            "time": 99752,
            "lane": 2
        },
        {
            "time": 99869,
            "lane": 1
        },
        {
            "time": 100101,
            "lane": 0
        },
        {
            "time": 100797,
            "lane": 3
        },
        {
            "time": 101122,
            "lane": 2
        },
        {
            "time": 101262,
            "lane": 1
        },
        {
            "time": 101703,
            "lane": 0
        },
        {
            "time": 101865,
            "lane": 1
        },
        {
            "time": 102051,
            "lane": 3
        },
        {
            "time": 102191,
            "lane": 0
        },
        {
            "time": 102307,
            "lane": 2
        },
        {
            "time": 102562,
            "lane": 1
        },
        {
            "time": 102678,
            "lane": 3
        },
        {
            "time": 102934,
            "lane": 1
        },
        {
            "time": 103096,
            "lane": 0
        },
        {
            "time": 103212,
            "lane": 3
        },
        {
            "time": 103421,
            "lane": 2
        },
        {
            "time": 103630,
            "lane": 3
        },
        {
            "time": 103769,
            "lane": 2
        },
        {
            "time": 103932,
            "lane": 3
        },
        {
            "time": 104095,
            "lane": 2
        },
        {
            "time": 104280,
            "lane": 3
        },
        {
            "time": 104513,
            "lane": 0
        },
        {
            "time": 104698,
            "lane": 3
        },
        {
            "time": 104861,
            "lane": 1
        },
        {
            "time": 106091,
            "lane": 0
        },
        {
            "time": 106811,
            "lane": 2
        },
        {
            "time": 107508,
            "lane": 3
        },
        {
            "time": 107856,
            "lane": 1
        },
        {
            "time": 108042,
            "lane": 3
        },
        {
            "time": 108181,
            "lane": 0
        },
        {
            "time": 108506,
            "lane": 3
        },
        {
            "time": 108739,
            "lane": 1
        },
        {
            "time": 109110,
            "lane": 0
        },
        {
            "time": 109226,
            "lane": 3
        },
        {
            "time": 109621,
            "lane": 1
        },
        {
            "time": 109807,
            "lane": 2
        },
        {
            "time": 110689,
            "lane": 3
        },
        {
            "time": 110875,
            "lane": 1
        },
        {
            "time": 111037,
            "lane": 2
        },
        {
            "time": 111386,
            "lane": 0
        },
        {
            "time": 111571,
            "lane": 1
        },
        {
            "time": 111711,
            "lane": 3
        },
        {
            "time": 111920,
            "lane": 2
        },
        {
            "time": 112082,
            "lane": 0
        },
        {
            "time": 112384,
            "lane": 3
        },
        {
            "time": 112802,
            "lane": 2
        },
        {
            "time": 113174,
            "lane": 3
        },
        {
            "time": 113336,
            "lane": 0
        },
        {
            "time": 113499,
            "lane": 1
        },
        {
            "time": 113684,
            "lane": 3
        },
        {
            "time": 113847,
            "lane": 0
        },
        {
            "time": 114218,
            "lane": 1
        },
        {
            "time": 114753,
            "lane": 0
        },
        {
            "time": 114915,
            "lane": 2
        },
        {
            "time": 115240,
            "lane": 3
        },
        {
            "time": 115565,
            "lane": 1
        },
        {
            "time": 115983,
            "lane": 0
        },
        {
            "time": 116146,
            "lane": 3
        },
        {
            "time": 116285,
            "lane": 2
        },
        {
            "time": 116494,
            "lane": 0
        },
        {
            "time": 116680,
            "lane": 3
        },
        {
            "time": 117028,
            "lane": 1
        },
        {
            "time": 117237,
            "lane": 3
        },
        {
            "time": 117376,
            "lane": 1
        },
        {
            "time": 117516,
            "lane": 0
        },
        {
            "time": 117701,
            "lane": 3
        },
        {
            "time": 117934,
            "lane": 2
        },
        {
            "time": 118027,
            "lane": 1
        },
        {
            "time": 118468,
            "lane": 2
        },
        {
            "time": 118584,
            "lane": 0
        },
        {
            "time": 118770,
            "lane": 2
        },
        {
            "time": 119164,
            "lane": 1
        },
        {
            "time": 119304,
            "lane": 0
        },
        {
            "time": 119513,
            "lane": 1
        },
        {
            "time": 119652,
            "lane": 3
        },
        {
            "time": 119814,
            "lane": 2
        },
        {
            "time": 120000,
            "lane": 3
        },
        {
            "time": 120349,
            "lane": 1
        },
        {
            "time": 120558,
            "lane": 3
        },
        {
            "time": 120883,
            "lane": 2
        },
        {
            "time": 121231,
            "lane": 0
        },
        {
            "time": 121626,
            "lane": 3
        },
        {
            "time": 121765,
            "lane": 2
        },
        {
            "time": 121997,
            "lane": 0
        },
        {
            "time": 122113,
            "lane": 3
        },
        {
            "time": 122253,
            "lane": 2
        },
        {
            "time": 122647,
            "lane": 0
        },
        {
            "time": 122996,
            "lane": 1
        },
        {
            "time": 123205,
            "lane": 2
        },
        {
            "time": 123367,
            "lane": 3
        },
        {
            "time": 123553,
            "lane": 1
        },
        {
            "time": 123669,
            "lane": 3
        },
        {
            "time": 124064,
            "lane": 0
        },
        {
            "time": 124458,
            "lane": 3
        },
        {
            "time": 124598,
            "lane": 0
        },
        {
            "time": 124807,
            "lane": 3
        },
        {
            "time": 124923,
            "lane": 1
        },
        {
            "time": 125155,
            "lane": 3
        },
        {
            "time": 125480,
            "lane": 0
        },
        {
            "time": 125875,
            "lane": 3
        },
        {
            "time": 126014,
            "lane": 0
        },
        {
            "time": 126223,
            "lane": 2
        },
        {
            "time": 126571,
            "lane": 0
        },
        {
            "time": 126757,
            "lane": 2
        },
        {
            "time": 126850,
            "lane": 3
        },
        {
            "time": 129195,
            "lane": 0
        },
        {
            "time": 129358,
            "lane": 2
        },
        {
            "time": 129567,
            "lane": 0
        },
        {
            "time": 129729,
            "lane": 2
        },
        {
            "time": 129915,
            "lane": 1
        },
        {
            "time": 144938,
            "lane": 0
        },
        {
            "time": 145124,
            "lane": 3
        },
        {
            "time": 145264,
            "lane": 0
        },
        {
            "time": 145635,
            "lane": 3
        },
        {
            "time": 145798,
            "lane": 2
        },
        {
            "time": 146169,
            "lane": 0
        },
        {
            "time": 146332,
            "lane": 3
        },
        {
            "time": 146819,
            "lane": 0
        },
        {
            "time": 147028,
            "lane": 3
        },
        {
            "time": 147353,
            "lane": 0
        },
        {
            "time": 147539,
            "lane": 3
        },
        {
            "time": 147725,
            "lane": 2
        },
        {
            "time": 147934,
            "lane": 1
        },
        {
            "time": 148120,
            "lane": 3
        },
        {
            "time": 148282,
            "lane": 0
        },
        {
            "time": 148630,
            "lane": 2
        },
        {
            "time": 148932,
            "lane": 1
        },
        {
            "time": 149095,
            "lane": 2
        },
        {
            "time": 149327,
            "lane": 0
        },
        {
            "time": 149699,
            "lane": 1
        },
        {
            "time": 149838,
            "lane": 3
        },
        {
            "time": 150372,
            "lane": 1
        },
        {
            "time": 150534,
            "lane": 2
        },
        {
            "time": 151278,
            "lane": 1
        },
        {
            "time": 151370,
            "lane": 0
        },
        {
            "time": 151974,
            "lane": 1
        },
        {
            "time": 152671,
            "lane": 0
        },
        {
            "time": 153228,
            "lane": 1
        },
        {
            "time": 153321,
            "lane": 3
        },
        {
            "time": 153483,
            "lane": 0
        },
        {
            "time": 154250,
            "lane": 3
        },
        {
            "time": 154435,
            "lane": 1
        },
        {
            "time": 154598,
            "lane": 2
        },
        {
            "time": 154784,
            "lane": 0
        },
        {
            "time": 155875,
            "lane": 1
        },
        {
            "time": 155968,
            "lane": 0
        },
        {
            "time": 156339,
            "lane": 2
        },
        {
            "time": 156572,
            "lane": 3
        },
        {
            "time": 156920,
            "lane": 0
        },
        {
            "time": 157686,
            "lane": 2
        },
        {
            "time": 160473,
            "lane": 1
        },
        {
            "time": 161843,
            "lane": 2
        },
        {
            "time": 162400,
            "lane": 0
        },
        {
            "time": 162748,
            "lane": 3
        },
        {
            "time": 162864,
            "lane": 2
        },
        {
            "time": 163259,
            "lane": 3
        },
        {
            "time": 163909,
            "lane": 1
        },
        {
            "time": 164350,
            "lane": 3
        },
        {
            "time": 164466,
            "lane": 2
        },
        {
            "time": 164675,
            "lane": 0
        },
        {
            "time": 165024,
            "lane": 3
        },
        {
            "time": 165349,
            "lane": 2
        },
        {
            "time": 165535,
            "lane": 0
        },
        {
            "time": 165744,
            "lane": 1
        },
        {
            "time": 166069,
            "lane": 0
        },
        {
            "time": 166440,
            "lane": 3
        },
        {
            "time": 166812,
            "lane": 0
        },
        {
            "time": 166997,
            "lane": 3
        },
        {
            "time": 167160,
            "lane": 1
        },
        {
            "time": 167276,
            "lane": 3
        },
        {
            "time": 167485,
            "lane": 1
        },
        {
            "time": 167857,
            "lane": 0
        },
        {
            "time": 168251,
            "lane": 3
        },
        {
            "time": 168391,
            "lane": 1
        },
        {
            "time": 168576,
            "lane": 3
        },
        {
            "time": 168878,
            "lane": 0
        },
        {
            "time": 169621,
            "lane": 1
        },
        {
            "time": 169807,
            "lane": 2
        },
        {
            "time": 169970,
            "lane": 3
        },
        {
            "time": 170109,
            "lane": 2
        },
        {
            "time": 170341,
            "lane": 3
        },
        {
            "time": 170643,
            "lane": 0
        },
        {
            "time": 170875,
            "lane": 1
        },
        {
            "time": 171038,
            "lane": 3
        },
        {
            "time": 171340,
            "lane": 1
        },
        {
            "time": 171572,
            "lane": 0
        },
        {
            "time": 171711,
            "lane": 2
        },
        {
            "time": 171827,
            "lane": 0
        },
        {
            "time": 172106,
            "lane": 1
        },
        {
            "time": 172268,
            "lane": 3
        },
        {
            "time": 172408,
            "lane": 2
        },
        {
            "time": 172826,
            "lane": 1
        },
        {
            "time": 172942,
            "lane": 2
        },
        {
            "time": 173127,
            "lane": 3
        },
        {
            "time": 173522,
            "lane": 1
        },
        {
            "time": 173662,
            "lane": 2
        },
        {
            "time": 173987,
            "lane": 3
        },
        {
            "time": 174196,
            "lane": 0
        },
        {
            "time": 174521,
            "lane": 2
        },
        {
            "time": 174869,
            "lane": 1
        },
        {
            "time": 175217,
            "lane": 2
        },
        {
            "time": 175426,
            "lane": 1
        },
        {
            "time": 175566,
            "lane": 2
        },
        {
            "time": 175751,
            "lane": 3
        },
        {
            "time": 175891,
            "lane": 0
        },
        {
            "time": 176285,
            "lane": 1
        },
        {
            "time": 176610,
            "lane": 0
        },
        {
            "time": 176866,
            "lane": 1
        },
        {
            "time": 177005,
            "lane": 2
        },
        {
            "time": 177214,
            "lane": 3
        },
        {
            "time": 177330,
            "lane": 2
        },
        {
            "time": 178073,
            "lane": 0
        },
        {
            "time": 178259,
            "lane": 1
        },
        {
            "time": 178445,
            "lane": 0
        },
        {
            "time": 178607,
            "lane": 1
        },
        {
            "time": 178816,
            "lane": 0
        },
        {
            "time": 179165,
            "lane": 1
        },
        {
            "time": 179513,
            "lane": 0
        },
        {
            "time": 179676,
            "lane": 3
        },
        {
            "time": 179861,
            "lane": 2
        },
        {
            "time": 180210,
            "lane": 3
        },
        {
            "time": 180395,
            "lane": 2
        },
        {
            "time": 180860,
            "lane": 3
        },
        {
            "time": 180999,
            "lane": 1
        },
        {
            "time": 181278,
            "lane": 0
        },
        {
            "time": 181394,
            "lane": 3
        },
        {
            "time": 181626,
            "lane": 1
        },
        {
            "time": 181928,
            "lane": 2
        },
        {
            "time": 182160,
            "lane": 0
        },
        {
            "time": 182299,
            "lane": 2
        },
        {
            "time": 182624,
            "lane": 1
        },
        {
            "time": 182857,
            "lane": 0
        },
        {
            "time": 183042,
            "lane": 3
        },
        {
            "time": 183367,
            "lane": 2
        },
        {
            "time": 183576,
            "lane": 3
        },
        {
            "time": 184412,
            "lane": 2
        },
        {
            "time": 184993,
            "lane": 3
        },
        {
            "time": 185341,
            "lane": 2
        },
        {
            "time": 185480,
            "lane": 3
        },
        {
            "time": 185852,
            "lane": 2
        },
        {
            "time": 186549,
            "lane": 3
        },
        {
            "time": 186920,
            "lane": 0
        },
        {
            "time": 187059,
            "lane": 2
        },
        {
            "time": 187268,
            "lane": 3
        },
        {
            "time": 187617,
            "lane": 2
        },
        {
            "time": 187942,
            "lane": 0
        },
        {
            "time": 188151,
            "lane": 2
        },
        {
            "time": 188244,
            "lane": 0
        },
        {
            "time": 188499,
            "lane": 1
        },
        {
            "time": 188662,
            "lane": 0
        },
        {
            "time": 189033,
            "lane": 1
        },
        {
            "time": 189149,
            "lane": 0
        },
        {
            "time": 189567,
            "lane": 3
        },
        {
            "time": 189753,
            "lane": 2
        },
        {
            "time": 189916,
            "lane": 1
        },
        {
            "time": 190055,
            "lane": 0
        },
        {
            "time": 190450,
            "lane": 3
        },
        {
            "time": 190821,
            "lane": 2
        },
        {
            "time": 190984,
            "lane": 1
        },
        {
            "time": 191146,
            "lane": 3
        },
        {
            "time": 191471,
            "lane": 0
        },
        {
            "time": 191611,
            "lane": 2
        },
        {
            "time": 192168,
            "lane": 3
        },
        {
            "time": 192539,
            "lane": 1
        },
        {
            "time": 192725,
            "lane": 3
        },
        {
            "time": 192911,
            "lane": 1
        },
        {
            "time": 193236,
            "lane": 3
        },
        {
            "time": 193445,
            "lane": 1
        },
        {
            "time": 194165,
            "lane": 2
        },
        {
            "time": 194931,
            "lane": 0
        }
    ]
}