{
    "title": "IDOL",
    "artist": "BLOOMIFY Engine",
    "mapper": "SmartGenerator",
    "audio_path": "song.mp3",
    "image_path": "art.png",
    "bpm": 89.1,
    "offset_ms": 580.5,
    "song_length_ms": 191100,
    "notes": [
        {
            "time": 4551,
            "lane": 1
        },
        {
            "time": 7221,
            "lane": 2
        },
        {
            "time": 9218,
            "lane": 3
        },
        {
            "time": 9566,
            "lane": 0
        },
        {
            "time": 18552,
            "lane": 2
        },
        {
            "time": 20201,
            "lane": 3
        },
        {
            "time": 23893,
            "lane": 0
        },
        {
            "time": 24636,
            "lane": 1
        },
        {
            "time": 25193,
            "lane": 3
        },
        {
            "time": 25379,
            "lane": 2
        },
        {
            "time": 25518,
            "lane": 0
        },
        {
            "time": 25704,
            "lane": 3
        },
        {
            "time": 25820,
            "lane": 2
        },
        {
            "time": 25936,
            "lane": 1
        },
        {
            "time": 26052,
            "lane": 2
        },
        {
            "time": 26517,
            "lane": 0
        },
        {
            "time": 26656,
            "lane": 2
        },
        {
            "time": 26865,
            "lane": 0
        },
        {
            "time": 27237,
            "lane": 2
        },
        {
            "time": 27329,
            "lane": 1
        },
        {
            "time": 27863,
            "lane": 2
        },
        {
            "time": 28398,
            "lane": 1
        },
        {
            "time": 28514,
            "lane": 2
        },
        {
            "time": 28699,
            "lane": 1
        },
        {
            "time": 28885,
            "lane": 0
        },
        {
            "time": 28978,
            "lane": 3
        },
        {
            "time": 29233,
            "lane": 2
        },
        {
            "time": 29373,
            "lane": 0
        },
        {
            "time": 29698,
            "lane": 2
        },
        {
            "time": 29860,
            "lane": 0
        },
        {
            "time": 31370,
            "lane": 2
        },
        {
            "time": 31555,
            "lane": 1
        },
        {
            "time": 32159,
            "lane": 2
        },
        {
            "time": 32391,
            "lane": 0
        },
        {
            "time": 32716,
            "lane": 2
        },
        {
            "time": 33204,
            "lane": 1
        },
        {
            "time": 34040,
            "lane": 3
        },
        {
            "time": 34528,
            "lane": 1
        },
        {
            "time": 34713,
            "lane": 0
        },
        {
            "time": 34876,
            "lane": 1
        },
        {
            "time": 35038,
            "lane": 2
        },
        {
            "time": 35224,
            "lane": 0
        },
        {
            "time": 35572,
            "lane": 2
        },
        {
            "time": 35828,
            "lane": 1
        },
        {
            "time": 36339,
            "lane": 3
        },
        {
            "time": 36710,
            "lane": 0
        },
        {
            "time": 36896,
            "lane": 3
        },
        {
            "time": 37221,
            "lane": 1
        },
        {
            "time": 37384,
            "lane": 0
        },
        {
            "time": 37848,
            "lane": 3
        },
        {
            "time": 38521,
            "lane": 0
        },
        {
            "time": 39381,
            "lane": 1
        },
        {
            "time": 39566,
            "lane": 0
        },
        {
            "time": 39868,
            "lane": 2
        },
        {
            "time": 39984,
            "lane": 1
        },
        {
            "time": 40147,
            "lane": 2
        },
        {
            "time": 40542,
            "lane": 1
        },
        {
            "time": 41192,
            "lane": 2
        },
        {
            "time": 42051,
            "lane": 0
        },
        {
            "time": 42167,
            "lane": 2
        },
        {
            "time": 43235,
            "lane": 0
        },
        {
            "time": 45557,
            "lane": 1
        },
        {
            "time": 46370,
            "lane": 3
        },
        {
            "time": 48227,
            "lane": 0
        },
        {
            "time": 48552,
            "lane": 3
        },
        {
            "time": 50039,
            "lane": 2
        },
        {
            "time": 50898,
            "lane": 3
        },
        {
            "time": 51246,
            "lane": 1
        },
        {
            "time": 53220,
            "lane": 3
        },
        {
            "time": 53730,
            "lane": 1
        },
        {
            "time": 53847,
            "lane": 3
        },
        {
            "time": 54566,
            "lane": 0
        },
        {
            "time": 54868,
            "lane": 3
        },
        {
            "time": 55240,
            "lane": 2
        },
        {
            "time": 56424,
            "lane": 3
        },
        {
            "time": 56517,
            "lane": 2
        },
        {
            "time": 56865,
            "lane": 1
        },
        {
            "time": 57724,
            "lane": 2
        },
        {
            "time": 57910,
            "lane": 3
        },
        {
            "time": 58003,
            "lane": 1
        },
        {
            "time": 58165,
            "lane": 2
        },
        {
            "time": 58560,
            "lane": 3
        },
        {
            "time": 58700,
            "lane": 2
        },
        {
            "time": 58862,
            "lane": 3
        },
        {
            "time": 59582,
            "lane": 2
        },
        {
            "time": 59721,
            "lane": 0
        },
        {
            "time": 60580,
            "lane": 3
        },
        {
            "time": 60696,
            "lane": 2
        },
        {
            "time": 61231,
            "lane": 1
        },
        {
            "time": 61393,
            "lane": 0
        },
        {
            "time": 62206,
            "lane": 3
        },
        {
            "time": 62740,
            "lane": 0
        },
        {
            "time": 62856,
            "lane": 1
        },
        {
            "time": 63065,
            "lane": 0
        },
        {
            "time": 63204,
            "lane": 3
        },
        {
            "time": 63367,
            "lane": 0
        },
        {
            "time": 63553,
            "lane": 3
        },
        {
            "time": 63901,
            "lane": 0
        },
        {
            "time": 64203,
            "lane": 1
        },
        {
            "time": 64528,
            "lane": 2
        },
        {
            "time": 64667,
            "lane": 3
        },
        {
            "time": 64899,
            "lane": 2
        },
        {
            "time": 65085,
            "lane": 0
        },
        {
            "time": 65201,
            "lane": 1
        },
        {
            "time": 65875,
            "lane": 3
        },
        {
            "time": 66014,
            "lane": 0
        },
        {
            "time": 66153,
            "lane": 2
        },
        {
            "time": 66362,
            "lane": 3
        },
        {
            "time": 66501,
            "lane": 0
        },
        {
            "time": 66710,
            "lane": 1
        },
        {
            "time": 67198,
            "lane": 0
        },
        {
            "time": 67523,
            "lane": 3
        },
        {
            "time": 67662,
            "lane": 0
        },
        {
            "time": 67871,
            "lane": 1
        },
        {
            "time": 68197,
            "lane": 0
        },
        {
            "time": 68684,
            "lane": 2
        },
        {
            "time": 68893,
            "lane": 3
        },
        {
            "time": 69032,
            "lane": 1
        },
        {
            "time": 69218,
            "lane": 3
        },
        {
            "time": 69358,
            "lane": 1
        },
        {
            "time": 69543,
            "lane": 0
        },
        {
            "time": 70240,
            "lane": 2
        },
        {
            "time": 70379,
            "lane": 0
        },
        {
            "time": 70519,
            "lane": 3
        },
        {
            "time": 70913,
            "lane": 0
        },
        {
            "time": 71354,
            "lane": 1
        },
        {
            "time": 71471,
            "lane": 3
        },
        {
            "time": 71888,
            "lane": 2
        },
        {
            "time": 72005,
            "lane": 0
        },
        {
            "time": 72515,
            "lane": 3
        },
        {
            "time": 72864,
            "lane": 0
        },
        {
            "time": 73212,
            "lane": 3
        },
        {
            "time": 73560,
            "lane": 2
        },
        {
            "time": 73700,
            "lane": 3
        },
        {
            "time": 73862,
            "lane": 1
        },
        {
            "time": 74048,
            "lane": 3
        },
        {
            "time": 74164,
            "lane": 2
        },
        {
            "time": 74559,
            "lane": 3
        },
        {
            "time": 74861,
            "lane": 1
        },
        {
            "time": 75557,
            "lane": 3
        },
        {
            "time": 75720,
            "lane": 1
        },
        {
            "time": 75859,
            "lane": 3
        },
        {
            "time": 76323,
            "lane": 1
        },
        {
            "time": 76556,
            "lane": 0
        },
        {
            "time": 76718,
            "lane": 3
        },
        {
            "time": 76811,
            "lane": 2
        },
        {
            "time": 77067,
            "lane": 0
        },
        {
            "time": 77856,
            "lane": 2
        },
        {
            "time": 78553,
            "lane": 0
        },
        {
            "time": 79690,
            "lane": 2
        },
        {
            "time": 79876,
            "lane": 1
        },
        {
            "time": 80735,
            "lane": 2
        },
        {
            "time": 80828,
            "lane": 1
        },
        {
            "time": 81037,
            "lane": 0
        },
        {
            "time": 82384,
            "lane": 1
        },
        {
            "time": 82523,
            "lane": 3
        },
        {
            "time": 82732,
            "lane": 0
        },
        {
            "time": 82872,
            "lane": 1
        },
        {
            "time": 83057,
            "lane": 2
        },
        {
            "time": 83220,
            "lane": 1
        },
        {
            "time": 83313,
            "lane": 0
        },
        {
            "time": 83870,
            "lane": 1
        },
        {
            "time": 84706,
            "lane": 3
        },
        {
            "time": 85008,
            "lane": 1
        },
        {
            "time": 85542,
            "lane": 0
        },
        {
            "time": 86076,
            "lane": 1
        },
        {
            "time": 86540,
            "lane": 3
        },
        {
            "time": 88677,
            "lane": 2
        },
        {
            "time": 88862,
            "lane": 1
        },
        {
            "time": 89071,
            "lane": 0
        },
        {
            "time": 89211,
            "lane": 1
        },
        {
            "time": 89512,
            "lane": 3
        },
        {
            "time": 89675,
            "lane": 1
        },
        {
            "time": 89838,
            "lane": 0
        },
        {
            "time": 90070,
            "lane": 1
        },
        {
            "time": 90186,
            "lane": 3
        },
        {
            "time": 90325,
            "lane": 2
        },
        {
            "time": 90511,
            "lane": 0
        },
        {
            "time": 90650,
            "lane": 1
        },
        {
            "time": 90906,
            "lane": 2
        },
        {
            "time": 91207,
            "lane": 1
        },
        {
            "time": 91347,
            "lane": 3
        },
        {
            "time": 91695,
            "lane": 0
        },
        {
            "time": 91904,
            "lane": 3
        },
        {
            "time": 92229,
            "lane": 0
        },
        {
            "time": 92392,
            "lane": 3
        },
        {
            "time": 92531,
            "lane": 0
        },
        {
            "time": 92717,
            "lane": 1
        },
        {
            "time": 92833,
            "lane": 2
        },
        {
            "time": 93042,
            "lane": 3
        },
        {
            "time": 93228,
            "lane": 0
        },
        {
            "time": 93367,
            "lane": 1
        },
        {
            "time": 93576,
            "lane": 2
        },
        {
            "time": 93878,
            "lane": 0
        },
        {
            "time": 95364,
            "lane": 2
        },
        {
            "time": 95875,
            "lane": 1
        },
        {
            "time": 96037,
            "lane": 3
        },
        {
            "time": 97872,
            "lane": 0
        },
        {
            "time": 98034,
            "lane": 3
        },
        {
            "time": 98243,
            "lane": 1
        },
        {
            "time": 98406,
            "lane": 3
        },
        {
            "time": 98545,
            "lane": 0
        },
        {
            "time": 98684,
            "lane": 2
        },
        {
            "time": 98893,
            "lane": 3
        },
        {
            "time": 99033,
            "lane": 2
        },
        {
            "time": 99497,
            "lane": 3
        },
        {
            "time": 99869,
            "lane": 1
        },
        {
            "time": 100194,
            "lane": 2
        },
        {
            "time": 100379,
            "lane": 1
        },
        {
            "time": 100565,
            "lane": 2
        },
        {
            "time": 100728,
            "lane": 0
        },
        {
            "time": 100890,
            "lane": 3
        },
        {
            "time": 101215,
            "lane": 0
        },
        {
            "time": 101401,
            "lane": 1
        },
        {
            "time": 101726,
            "lane": 0
        },
        {
            "time": 101819,
            "lane": 1
        },
        {
            "time": 102353,
            "lane": 0
        },
        {
            "time": 102539,
            "lane": 3
        },
        {
            "time": 102864,
            "lane": 2
        },
        {
            "time": 103026,
            "lane": 1
        },
        {
            "time": 103375,
            "lane": 2
        },
        {
            "time": 103468,
            "lane": 0
        },
        {
            "time": 103839,
            "lane": 2
        },
        {
            "time": 104048,
            "lane": 3
        },
        {
            "time": 104350,
            "lane": 0
        },
        {
            "time": 104536,
            "lane": 1
        },
        {
            "time": 104745,
            "lane": 3
        },
        {
            "time": 105743,
            "lane": 0
        },
        {
            "time": 105859,
            "lane": 1
        },
        {
            "time": 106068,
            "lane": 3
        },
        {
            "time": 106556,
            "lane": 2
        },
        {
            "time": 107067,
            "lane": 0
        },
        {
            "time": 107508,
            "lane": 1
        },
        {
            "time": 107833,
            "lane": 2
        },
        {
            "time": 108553,
            "lane": 3
        },
        {
            "time": 109226,
            "lane": 0
        },
        {
            "time": 109528,
            "lane": 2
        },
        {
            "time": 109760,
            "lane": 0
        },
        {
            "time": 109830,
            "lane": 1
        },
        {
            "time": 110364,
            "lane": 3
        },
        {
            "time": 110550,
            "lane": 2
        },
        {
            "time": 110875,
            "lane": 0
        },
        {
            "time": 111177,
            "lane": 1
        },
        {
            "time": 111362,
            "lane": 2
        },
        {
            "time": 111502,
            "lane": 3
        },
        {
            "time": 111873,
            "lane": 2
        },
        {
            "time": 112222,
            "lane": 1
        },
        {
            "time": 112547,
            "lane": 3
        },
        {
            "time": 113011,
            "lane": 0
        },
        {
            "time": 113150,
            "lane": 2
        },
        {
            "time": 113522,
            "lane": 1
        },
        {
            "time": 113870,
            "lane": 3
        },
        {
            "time": 114033,
            "lane": 1
        },
        {
            "time": 114567,
            "lane": 3
        },
        {
            "time": 114706,
            "lane": 0
        },
        {
            "time": 114869,
            "lane": 1
        },
        {
            "time": 115008,
            "lane": 0
        },
        {
            "time": 115217,
            "lane": 3
        },
        {
            "time": 115705,
            "lane": 2
        },
        {
            "time": 115867,
            "lane": 0
        },
        {
            "time": 116215,
            "lane": 2
        },
        {
            "time": 116494,
            "lane": 0
        },
        {
            "time": 116657,
            "lane": 3
        },
        {
            "time": 117167,
            "lane": 1
        },
        {
            "time": 117562,
            "lane": 2
        },
        {
            "time": 117864,
            "lane": 1
        },
        {
            "time": 118027,
            "lane": 3
        },
        {
            "time": 118166,
            "lane": 1
        },
        {
            "time": 118352,
            "lane": 0
        },
        {
            "time": 118491,
            "lane": 2
        },
        {
            "time": 118839,
            "lane": 1
        },
        {
            "time": 119211,
            "lane": 0
        },
        {
            "time": 120418,
            "lane": 2
        },
        {
            "time": 120534,
            "lane": 0
        },
        {
            "time": 120859,
            "lane": 1
        },
        {
            "time": 121208,
            "lane": 0
        },
        {
            "time": 121742,
            "lane": 2
        },
        {
            "time": 121927,
            "lane": 3
        },
        {
            "time": 122020,
            "lane": 2
        },
        {
            "time": 122160,
            "lane": 0
        },
        {
            "time": 122554,
            "lane": 1
        },
        {
            "time": 123576,
            "lane": 3
        },
        {
            "time": 123715,
            "lane": 0
        },
        {
            "time": 124714,
            "lane": 1
        },
        {
            "time": 125225,
            "lane": 0
        },
        {
            "time": 125410,
            "lane": 2
        },
        {
            "time": 125898,
            "lane": 1
        },
        {
            "time": 126200,
            "lane": 3
        },
        {
            "time": 126548,
            "lane": 0
        },
        {
            "time": 126897,
            "lane": 2
        },
        {
            "time": 127059,
            "lane": 1
        },
        {
            "time": 127198,
            "lane": 3
        },
        {
            "time": 127361,
            "lane": 2
        },
        {
            "time": 127547,
            "lane": 1
        },
        {
            "time": 127895,
            "lane": 0
        },
        {
            "time": 128220,
            "lane": 3
        },
        {
            "time": 128731,
            "lane": 0
        },
        {
            "time": 128893,
            "lane": 3
        },
        {
            "time": 129079,
            "lane": 0
        },
        {
            "time": 129195,
            "lane": 3
        },
        {
            "time": 129985,
            "lane": 0
        },
        {
            "time": 130240,
            "lane": 3
        },
        {
            "time": 130496,
            "lane": 0
        },
        {
            "time": 131146,
            "lane": 1
        },
        {
            "time": 131494,
            "lane": 3
        },
        {
            "time": 131657,
            "lane": 2
        },
        {
            "time": 131866,
            "lane": 1
        },
        {
            "time": 132702,
            "lane": 3
        },
        {
            "time": 132887,
            "lane": 2
        },
        {
            "time": 133027,
            "lane": 3
        },
        {
            "time": 133537,
            "lane": 1
        },
        {
            "time": 134002,
            "lane": 0
        },
        {
            "time": 134234,
            "lane": 1
        },
        {
            "time": 134513,
            "lane": 3
        },
        {
            "time": 134907,
            "lane": 1
        },
        {
            "time": 135256,
            "lane": 0
        },
        {
            "time": 135349,
            "lane": 3
        },
        {
            "time": 135488,
            "lane": 1
        },
        {
            "time": 135906,
            "lane": 2
        },
        {
            "time": 136533,
            "lane": 3
        },
        {
            "time": 136719,
            "lane": 0
        },
        {
            "time": 136835,
            "lane": 2
        },
        {
            "time": 137671,
            "lane": 0
        },
        {
            "time": 137856,
            "lane": 3
        },
        {
            "time": 138019,
            "lane": 2
        },
        {
            "time": 138158,
            "lane": 1
        },
        {
            "time": 138553,
            "lane": 0
        },
        {
            "time": 138808,
            "lane": 3
        },
        {
            "time": 139203,
            "lane": 1
        },
        {
            "time": 139389,
            "lane": 2
        },
        {
            "time": 139575,
            "lane": 0
        },
        {
            "time": 139714,
            "lane": 1
        },
        {
            "time": 140411,
            "lane": 2
        },
        {
            "time": 140736,
            "lane": 1
        },
        {
            "time": 140805,
            "lane": 3
        },
        {
            "time": 141014,
            "lane": 1
        },
        {
            "time": 141386,
            "lane": 2
        },
        {
            "time": 141897,
            "lane": 0
        },
        {
            "time": 142222,
            "lane": 3
        },
        {
            "time": 142384,
            "lane": 1
        },
        {
            "time": 142570,
            "lane": 0
        },
        {
            "time": 142918,
            "lane": 2
        },
        {
            "time": 143034,
            "lane": 3
        },
        {
            "time": 143731,
            "lane": 1
        },
        {
            "time": 143894,
            "lane": 3
        },
        {
            "time": 144729,
            "lane": 2
        },
        {
            "time": 144846,
            "lane": 0
        },
        {
            "time": 145055,
            "lane": 3
        },
        {
            "time": 145217,
            "lane": 1
        },
        {
            "time": 145519,
            "lane": 0
        },
        {
            "time": 145658,
            "lane": 2
        },
        {
            "time": 145844,
            "lane": 0
        },
        {
            "time": 146401,
            "lane": 2
        },
        {
            "time": 146564,
            "lane": 0
        },
        {
            "time": 146889,
            "lane": 1
        },
        {
            "time": 147075,
            "lane": 0
        },
        {
            "time": 147562,
            "lane": 2
        },
        {
            "time": 147748,
            "lane": 1
        },
        {
            "time": 147887,
            "lane": 2
        },
        {
            "time": 148189,
            "lane": 1
        },
        {
            "time": 148352,
            "lane": 0
        },
        {
            "time": 148561,
            "lane": 2
        },
        {
            "time": 148909,
            "lane": 0
        },
        {
            "time": 149211,
            "lane": 1
        },
        {
            "time": 149559,
            "lane": 3
        },
        {
            "time": 150070,
            "lane": 1
        },
        {
            "time": 150163,
            "lane": 0
        },
        {
            "time": 150325,
            "lane": 1
        },
        {
            "time": 150558,
            "lane": 2
        },
        {
            "time": 150860,
            "lane": 0
        },
        {
            "time": 150999,
            "lane": 1
        },
        {
            "time": 152531,
            "lane": 3
        },
        {
            "time": 152880,
            "lane": 2
        },
        {
            "time": 153530,
            "lane": 3
        },
        {
            "time": 154203,
            "lane": 1
        },
        {
            "time": 154552,
            "lane": 3
        },
        {
            "time": 154900,
            "lane": 2
        },
        {
            "time": 155898,
            "lane": 3
        },
        {
            "time": 156200,
            "lane": 2
        },
        {
            "time": 156548,
            "lane": 3
        },
        {
            "time": 156850,
            "lane": 2
        },
        {
            "time": 157222,
            "lane": 1
        },
        {
            "time": 157524,
            "lane": 3
        },
        {
            "time": 158383,
            "lane": 1
        },
        {
            "time": 159404,
            "lane": 2
        },
        {
            "time": 159544,
            "lane": 1
        },
        {
            "time": 160194,
            "lane": 3
        },
        {
            "time": 160519,
            "lane": 0
        },
        {
            "time": 160891,
            "lane": 3
        },
        {
            "time": 161216,
            "lane": 0
        },
        {
            "time": 161564,
            "lane": 1
        },
        {
            "time": 161843,
            "lane": 2
        },
        {
            "time": 164374,
            "lane": 0
        },
        {
            "time": 165395,
            "lane": 1
        },
        {
            "time": 166510,
            "lane": 0
        },
        {
            "time": 166905,
            "lane": 1
        },
        {
            "time": 167230,
            "lane": 2
        },
        {
            "time": 167903,
            "lane": 3
        },
        {
            "time": 168553,
            "lane": 0
        },
        {
            "time": 169528,
            "lane": 3
        },
        {
            "time": 169877,
            "lane": 2
        },
        {
            "time": 170550,
            "lane": 0
        },
        {
            "time": 170875,
            "lane": 3
        },
        {
            "time": 171038,
            "lane": 1
        },
        {
            "time": 171200,
            "lane": 3
        },
        {
            "time": 171572,
            "lane": 2
        },
        {
            "time": 171850,
            "lane": 0
        },
        {
            "time": 172222,
            "lane": 1
        },
        {
            "time": 172315,
            "lane": 0
        },
        {
            "time": 172524,
            "lane": 3
        },
        {
            "time": 173220,
            "lane": 0
        },
        {
            "time": 173522,
            "lane": 2
        },
        {
            "time": 173708,
            "lane": 0
        },
        {
            "time": 174869,
            "lane": 3
        },
        {
            "time": 175032,
            "lane": 0
        },
        {
            "time": 175194,
            "lane": 1
        },
        {
            "time": 175519,
            "lane": 2
        },
        {
            "time": 175867,
            "lane": 3
        },
        {
            "time": 176193,
            "lane": 2
        },
        {
            "time": 176401,
            "lane": 1
        },
        {
            "time": 176912,
            "lane": 0
        },
        {
            "time": 177864,
            "lane": 1
        },
        {
            "time": 178166,
            "lane": 0
        },
        {
            "time": 178491,
            "lane": 3
        },
        {
            "time": 179234,
            "lane": 0
        },
        {
            "time": 179559,
            "lane": 2
        },
        {
            "time": 179884,
            "lane": 1
        },
        {
            "time": 180163,
            "lane": 2
        },
        {
            "time": 180488,
            "lane": 1
        },
        {
            "time": 180813,
            "lane": 2
        },
        {
            "time": 181185,
            "lane": 3
        },
        {
            "time": 182183,
            "lane": 1
        },
        {
            "time": 182532,
            "lane": 2
        },
        {
            "time": 182833,
            "lane": 0
        },
        {
            "time": 183066,
            "lane": 3
        }
    ]
}